codecalculator/__init__.py
codecalculator-0.1.dist-info/LICENSE.txt
codecalculator-0.1.dist-info/METADATA
codecalculator-0.1.dist-info/WHEEL
codecalculator-0.1.dist-info/top_level.txt
codecalculator-0.1.dist-info/RECORD
