Metadata-Version: 2.1
Name: codecalculator
Version: 0.1
Summary: <This is a very basic calculator>
Author: <Abscordida
Author-email: <nyancheraabscordida@gmail.com
Classifier: Programming Language :: Python :: 3
Classifier: License :: OSI Approved :: MIT License
Classifier: Operating System :: OS Independent
License-File: LICENSE.txt
